sigtool/__init__.py
sigtool/apk_info_extractor.py
sigtool/apk_signature_extractor.py
sigtool/base64_encoder.py
sigtool/colon_uppercase.py
sigtool/crc32_and_hashcode_calculator.py
sigtool/main.py
sigtool/output_formatter.py
sigtool/pem_certificate_generator.py
sigtool/pem_signature_extractor.py
sigtool/signature_hash_calculator.py
sigtool/smali_bytearray_generator.py
sigtool/lib/smali.jar
sigtool/sighooks/__init__.py
sigtool/sighooks/mt_enhanced_hook/__init__.py
sigtool/sighooks/mt_enhanced_hook/mthook.py
sigtool/sighooks/mt_enhanced_hook/mthook_generator.py
sigtool-3.0.dist-info/LICENSE
sigtool-3.0.dist-info/METADATA
sigtool-3.0.dist-info/WHEEL
sigtool-3.0.dist-info/entry_points.txt
sigtool-3.0.dist-info/top_level.txt
sigtool-3.0.dist-info/RECORD
