Metadata-Version: 2.1
Name: sigtool
Version: 3.0
Summary: A command-line tool for in-depth APK signature and keystore analysis.
Author-email: MuhammadRizwan <mrizwan87@protonmail.com>
License: MIT License
Project-URL: homepage, https://github.com/muhammadrizwan87/sigtool
Classifier: Programming Language :: Python
Classifier: Programming Language :: Python :: 3
Classifier: License :: OSI Approved :: MIT License
Classifier: Operating System :: OS Independent
License-File: LICENSE
